{
  "type" : "FeatureCollection",
  "features" : [ {
    "type" : "Feature",
    "geometry" : {
      "type" : "Point",
      "coordinates" : [ 8.6702592175, 49.8819996044 ]
    },
    "properties" : {
      "type" : "place",
      "startTime" : "20141006T131309+0200",
      "endTime" : "20141007T115802+0200",
      "place" : {
        "id" : 251291724,
        "name" : "Home",
        "type" : "home",
        "location" : {
          "lat" : 49.8819996044,
          "lon" : 8.6702592175
        }
      },
      "lastUpdate" : "20141007T114220Z",
      "date" : "20141007"
    }
  }, {
    "type" : "Feature",
    "geometry" : {
      "type" : "Point",
      "coordinates" : [ 8.665967, 49.882194 ]
    },
    "properties" : {
      "type" : "place",
      "startTime" : "20141007T120340+0200",
      "endTime" : "20141007T120920+0200",
      "place" : {
        "id" : 251292369,
        "name" : "H Karlshof",
        "type" : "foursquare",
        "foursquareId" : "4d31931eb60937045413eddf",
        "location" : {
          "lat" : 49.882194,
          "lon" : 8.665967
        }
      },
      "lastUpdate" : "20141007T114220Z",
      "date" : "20141007"
    }
  }, {
    "type" : "Feature",
    "geometry" : {
      "type" : "Point",
      "coordinates" : [ 8.6551163231, 49.8728270312 ]
    },
    "properties" : {
      "type" : "place",
      "startTime" : "20141007T122238+0200",
      "endTime" : "20141007T133734+0200",
      "place" : {
        "id" : 225196872,
        "type" : "unknown",
        "location" : {
          "lat" : 49.8728270312,
          "lon" : 8.6551163231
        }
      },
      "lastUpdate" : "20141007T132153Z",
      "date" : "20141007"
    }
  }, {
    "type" : "Feature",
    "geometry" : {
      "type" : "Point",
      "coordinates" : [ 8.6605648722, 49.8742715717 ]
    },
    "properties" : {
      "type" : "place",
      "startTime" : "20141007T134430+0200",
      "endTime" : "20141007T140049+0200",
      "place" : {
        "id" : 227329234,
        "name" : "KOM Lab",
        "type" : "work",
        "location" : {
          "lat" : 49.8742715717,
          "lon" : 8.6605648722
        }
      },
      "lastUpdate" : "20141007T132153Z",
      "date" : "20141007"
    }
  }, {
    "type" : "Feature",
    "geometry" : {
      "type" : "Point",
      "coordinates" : [ 8.6697071135, 49.8824855756 ]
    },
    "properties" : {
      "type" : "place",
      "startTime" : "20141007T140848+0200",
      "endTime" : "20141009T083123+0200",
      "place" : {
        "id" : 260869940,
        "type" : "unknown",
        "location" : {
          "lat" : 49.8824855756,
          "lon" : 8.6697071135
        }
      },
      "lastUpdate" : "20141009T093705Z",
      "date" : "20141007"
    }
  } ]
}