{
  "type" : "FeatureCollection",
  "features" : [ {
    "type" : "Feature",
    "geometry" : {
      "type" : "Point",
      "coordinates" : [ 8.6702592175, 49.8819996044 ]
    },
    "properties" : {
      "type" : "place",
      "startTime" : "20140910T184728+0200",
      "endTime" : "20140911T083054+0200",
      "place" : {
        "id" : 251291724,
        "name" : "Home",
        "type" : "home",
        "location" : {
          "lat" : 49.8819996044,
          "lon" : 8.6702592175
        }
      },
      "lastUpdate" : "20140911T075213Z",
      "date" : "20140911"
    }
  }, {
    "type" : "Feature",
    "geometry" : {
      "type" : "Point",
      "coordinates" : [ 8.6249912643, 49.8712952279 ]
    },
    "properties" : {
      "type" : "place",
      "startTime" : "20140911T090314+0200",
      "endTime" : "20140911T174845+0200",
      "place" : {
        "id" : 249718361,
        "name" : "Consetto",
        "type" : "work",
        "location" : {
          "lat" : 49.8712952279,
          "lon" : 8.6249912643
        }
      },
      "lastUpdate" : "20140911T181207Z",
      "date" : "20140911"
    }
  }, {
    "type" : "Feature",
    "geometry" : {
      "type" : "Point",
      "coordinates" : [ 8.6506784424, 49.8721352336 ]
    },
    "properties" : {
      "type" : "place",
      "startTime" : "20140911T180458+0200",
      "endTime" : "20140911T181256+0200",
      "place" : {
        "id" : 255635054,
        "type" : "unknown",
        "location" : {
          "lat" : 49.8721352336,
          "lon" : 8.6506784424
        }
      },
      "lastUpdate" : "20140911T181207Z",
      "date" : "20140911"
    }
  }, {
    "type" : "Feature",
    "geometry" : {
      "type" : "Point",
      "coordinates" : [ 8.6532179149, 49.8707852336 ]
    },
    "properties" : {
      "type" : "place",
      "startTime" : "20140911T181717+0200",
      "endTime" : "20140911T183453+0200",
      "place" : {
        "id" : 225933586,
        "type" : "unknown",
        "location" : {
          "lat" : 49.8707852336,
          "lon" : 8.6532179149
        }
      },
      "lastUpdate" : "20140911T181207Z",
      "date" : "20140911"
    }
  }, {
    "type" : "Feature",
    "geometry" : {
      "type" : "Point",
      "coordinates" : [ 8.6551462382, 49.8713664158 ]
    },
    "properties" : {
      "type" : "place",
      "startTime" : "20140911T183842+0200",
      "endTime" : "20140911T190401+0200",
      "place" : {
        "id" : 255635055,
        "type" : "unknown",
        "location" : {
          "lat" : 49.8713664158,
          "lon" : 8.6551462382
        }
      },
      "lastUpdate" : "20140911T181207Z",
      "date" : "20140911"
    }
  }, {
    "type" : "Feature",
    "geometry" : {
      "type" : "Point",
      "coordinates" : [ 8.6702592175, 49.8819996044 ]
    },
    "properties" : {
      "type" : "place",
      "startTime" : "20140911T192254+0200",
      "endTime" : "20140912T015754+0200",
      "place" : {
        "id" : 251291724,
        "name" : "Home",
        "type" : "home",
        "location" : {
          "lat" : 49.8819996044,
          "lon" : 8.6702592175
        }
      },
      "lastUpdate" : "20140912T101312Z",
      "date" : "20140911"
    }
  } ]
}