{
  "type" : "FeatureCollection",
  "features" : [ {
    "type" : "Feature",
    "geometry" : {
      "type" : "Point",
      "coordinates" : [ 8.6702592175, 49.8819996044 ]
    },
    "properties" : {
      "type" : "place",
      "startTime" : "20140830T102403+0200",
      "endTime" : "20140831T193134+0200",
      "place" : {
        "id" : 251291724,
        "name" : "Home",
        "type" : "home",
        "location" : {
          "lat" : 49.8819996044,
          "lon" : 8.6702592175
        }
      },
      "lastUpdate" : "20140831T184927Z",
      "date" : "20140831"
    }
  }, {
    "type" : "Feature",
    "geometry" : {
      "type" : "Point",
      "coordinates" : [ 8.6675185755, 49.8826210232 ]
    },
    "properties" : {
      "type" : "place",
      "startTime" : "20140831T200811+0200",
      "endTime" : "20140901T165840+0200",
      "place" : {
        "id" : 223135125,
        "name" : "Volleyball field of Karlshof",
        "type" : "user",
        "location" : {
          "lat" : 49.8826210232,
          "lon" : 8.6675185755
        }
      },
      "lastUpdate" : "20140901T180045Z",
      "date" : "20140831"
    }
  } ]
}