{
  "type" : "FeatureCollection",
  "features" : [ {
    "type" : "Feature",
    "geometry" : {
      "type" : "Point",
      "coordinates" : [ 8.6702592175, 49.8819996044 ]
    },
    "properties" : {
      "type" : "place",
      "startTime" : "20141022T210855+0200",
      "endTime" : "20141023T083134+0200",
      "place" : {
        "id" : 251291724,
        "name" : "Home",
        "type" : "home",
        "location" : {
          "lat" : 49.8819996044,
          "lon" : 8.6702592175
        }
      },
      "lastUpdate" : "20141023T074305Z",
      "date" : "20141023"
    }
  }, {
    "type" : "Feature",
    "geometry" : {
      "type" : "Point",
      "coordinates" : [ 8.6249912643, 49.8712952279 ]
    },
    "properties" : {
      "type" : "place",
      "startTime" : "20141023T090117+0200",
      "endTime" : "20141023T125931+0200",
      "place" : {
        "id" : 249718361,
        "name" : "Consetto",
        "type" : "work",
        "location" : {
          "lat" : 49.8712952279,
          "lon" : 8.6249912643
        }
      },
      "lastUpdate" : "20141023T120914Z",
      "date" : "20141023"
    }
  }, {
    "type" : "Feature",
    "geometry" : {
      "type" : "Point",
      "coordinates" : [ 8.654577692, 49.877662904 ]
    },
    "properties" : {
      "type" : "place",
      "startTime" : "20141023T133246+0200",
      "endTime" : "20141023T140415+0200",
      "place" : {
        "id" : 223098012,
        "type" : "unknown",
        "location" : {
          "lat" : 49.877662904,
          "lon" : 8.654577692
        }
      },
      "lastUpdate" : "20141023T181212Z",
      "date" : "20141023"
    }
  }, {
    "type" : "Feature",
    "geometry" : {
      "type" : "Point",
      "coordinates" : [ 8.6582282669, 49.8776087749 ]
    },
    "properties" : {
      "type" : "place",
      "startTime" : "20141023T140752+0200",
      "endTime" : "20141023T142040+0200",
      "place" : {
        "id" : 271227991,
        "type" : "unknown",
        "location" : {
          "lat" : 49.8776087749,
          "lon" : 8.6582282669
        }
      },
      "lastUpdate" : "20141023T181212Z",
      "date" : "20141023"
    }
  }, {
    "type" : "Feature",
    "geometry" : {
      "type" : "Point",
      "coordinates" : [ 8.6702592175, 49.8819996044 ]
    },
    "properties" : {
      "type" : "place",
      "startTime" : "20141023T143020+0200",
      "endTime" : "20141024T083338+0200",
      "place" : {
        "id" : 251291724,
        "name" : "Home",
        "type" : "home",
        "location" : {
          "lat" : 49.8819996044,
          "lon" : 8.6702592175
        }
      },
      "lastUpdate" : "20141024T074211Z",
      "date" : "20141023"
    }
  } ]
}